outcome/__init__.py
outcome/outcome.py
outcome_tb-0.0.1.dist-info/LICENSE
outcome_tb-0.0.1.dist-info/METADATA
outcome_tb-0.0.1.dist-info/WHEEL
outcome_tb-0.0.1.dist-info/top_level.txt
outcome_tb-0.0.1.dist-info/RECORD
