Metadata-Version: 2.1
Name: outcome_tb
Version: 0.0.1
Summary: A simple package for the outcome data type
Author-email: Thomas Brumbaugh <thomas.william.brumbaugh@gmail.com>
Project-URL: Homepage, https://github.com/pypa/outcome_tb
Project-URL: Issues, https://github.com/pypa/outcome_tb/issues
Classifier: Programming Language :: Python :: 3
Classifier: License :: OSI Approved :: MIT License
Classifier: Operating System :: OS Independent
Requires-Python: >=3.8
License-File: LICENSE
